p3g/__init__.py
p3g/client.py
p3g-1.6.0.dist-info/LICENSE
p3g-1.6.0.dist-info/METADATA
p3g-1.6.0.dist-info/WHEEL
p3g-1.6.0.dist-info/entry_points.txt
p3g-1.6.0.dist-info/RECORD
