Metadata-Version: 2.1
Name: p3g
Version: 1.6.0
Summary: Python Packages Project Generator
Home-page: https://github.com/Undertone0809/P3G
License: MIT
Keywords: python,3pg,p3g,ruff,cookiecutter,template,packages,makefile,best-practices,poetry,codestyle,formatters,python-packages,semantic-versions
Author: Zeeland
Author-email: zeeland4work@gmail.com
Requires-Python: >=3.8,<4.0
Classifier: License :: OSI Approved :: MIT License
Classifier: Programming Language :: Python :: 3
Classifier: Programming Language :: Python :: 3.8
Classifier: Programming Language :: Python :: 3.9
Classifier: Programming Language :: Python :: 3.10
Classifier: Programming Language :: Python :: 3.11
Classifier: Programming Language :: Python :: 3.12
Requires-Dist: cookiecutter (>=2.6.0,<3.0.0)
Project-URL: Repository, https://github.com/Undertone0809/P3G
